multiplier.v
/*16 bit multiplier using data path and control path*/

/*  ///////  WELCOME  ////////*/


`timescale 1ns/1ps


module mul_data (equalZ,loadA,loadB,loadP,clrP,decB,data_in,clk);                // output and input to the data path
input loadA,loadB,loadP,clrP,decB,clk;
input[15:0] data_in;
output equalZ;
wire [15:0] X,Y,Z,Bout,bus;
assign bus= data_in;
  PIPO1 A (.dout(X),.d_in(bus),.ld(loadA),.clk(clk));                          // parallel in and parallel op register A
  PIPO2 P (.dout(Y),.din(Z),.ld(loadP),.clr(clrP),.clk(clk));                  // parallel in and parallel op register P
  CNTR B (.Bout(Bout),.data_in(bus),.ld(loadB),.decB(decB),.clk(clk));         // counter
  Add AD (.out(Z),.in1(X),.in2(Y));                                            // adder
  EqualZ COMP (.equalZ(equalZ),.Bout(Bout));                                   // comparator
endmodule




module PIPO1 (dout,d_in,ld,clk);                                              // module parallel in and parallel op register A
input [15:0] d_in;
input ld,clk;
output reg [15:0] dout;
always@(posedge clk)
if (ld) dout<=d_in;
endmodule




module PIPO2 (dout,din,ld,clr,clk);                                        // module parallel in and parallel op register P
input [15:0] din;
input ld,clr,clk;
output reg [15:0] dout;
always@(posedge clk)
if(clr) dout<=16'b0;
else if(ld) dout<=din;
endmodule



module Add (out,in1,in2);                                              // adder module
input [15:0] in1,in2;
output reg [15:0] out;
always @(*)
out=in1+in2;
endmodule



module EqualZ (equalZ,Bout);                                          //comparator module
input [15:0]Bout;
output equalZ;
assign equalZ=(Bout==1);
endmodule



module CNTR (Bout,data_in,ld,decB,clk);                          // counter module
input [15:0] data_in;
input ld,decB,clk;
output reg [15:0] Bout;
always @(posedge clk)
if(ld) Bout<=data_in;
else if (decB) Bout<=Bout-1;
endmodule




module controller (loadA,loadB,loadP,clrP,decB,done,clk,equalZ,start);                // controller module output and input
input clk,equalZ,start; 
output reg loadA,loadB,loadP,clrP,decB,done;
reg [2:0] state;
parameter S0=3'b000,S1=3'b001,S2=3'b010,S3=3'b011,S4=3'b100;
always@(posedge clk)
begin
case (state)
  S0: if (start) state<=S1;                                    // if start =1 we will move to state S1 
  S1: state<=S2;                                                                              
  S2: state<=S3;  
  S3: if (equalZ) state<=S4;                                  // remain in state S3 until equalZ=1
  S4: state<=S4; 
  default: state<=S0;
endcase
end
always @ (state)
begin
case (state)
S0: begin #1 loadA=0;loadB=0;loadP=0;clrP=0;decB=0; end
S1: begin #1 loadA=1; end
S2: begin #1 loadA=0;loadB=1;clrP=1; end
S3: begin #1 loadB=0;loadP=1;clrP=0;decB=1; end
S4: begin #1 done=1;loadB=0;loadP=0;decB=0; end
default: begin #1 loadA=0;loadB=0;loadP=0;clrP=0;decB=0; end
endcase
end
endmodule

multiplier_tb.v
//testbench for multiplier using data path and control path


`timescale 1ns/1ps
`include "control_data.v"


module mul_test;
reg [15:0] data_in;
reg clk, start;
wire done;
mul_data DP(equalZ,loadA,loadB,loadP,clrP,decB,data_in,clk);
controller CON (loadA,loadB,loadP,clrP,decB,done,clk,equalZ,start);
initial
  begin
    clk=1'b0;                  // setting the initial value of the clock
    #3 start=1'b1;             // set the start signal to to 1 to start the operation
    #100 $finish;              // finish the operation at 100ns
  end
always #5 clk=~clk;        // toggling the clock every 5ns
  initial 
    begin 
      #10 data_in=15;           // data in is provided on the bus
      #20 data_in=9;
    end
initial
   begin
     $monitor($time,"%d %b", DP.Y,done);                  // to see the output on the moniter 
     $dumpfile("mul.vcd"); $dumpvars (0,mul_test);        // variable values dump
   end
endmodule

mul.vcd
$date
	Fri Mar 26 21:59:30 2021
$end
$version
	Icarus Verilog
$end
$timescale
	1ps
$end
$scope module mul_test $end
$var wire 1 ! loadP $end
$var wire 1 " loadB $end
$var wire 1 # loadA $end
$var wire 1 $ equalZ $end
$var wire 1 % done $end
$var wire 1 & decB $end
$var wire 1 ' clrP $end
$var reg 1 ( clk $end
$var reg 16 ) data_in [15:0] $end
$var reg 1 * start $end
$scope module CON $end
$var wire 1 ( clk $end
$var wire 1 * start $end
$var wire 1 $ equalZ $end
$var reg 1 ' clrP $end
$var reg 1 & decB $end
$var reg 1 % done $end
$var reg 1 # loadA $end
$var reg 1 " loadB $end
$var reg 1 ! loadP $end
$var reg 3 + state [2:0] $end
$upscope $end
$scope module DP $end
$var wire 16 , bus [15:0] $end
$var wire 1 ( clk $end
$var wire 1 ' clrP $end
$var wire 16 - data_in [15:0] $end
$var wire 1 & decB $end
$var wire 1 # loadA $end
$var wire 1 " loadB $end
$var wire 1 ! loadP $end
$var wire 1 $ equalZ $end
$var wire 16 . Z [15:0] $end
$var wire 16 / Y [15:0] $end
$var wire 16 0 X [15:0] $end
$var wire 16 1 Bout [15:0] $end
$scope module A $end
$var wire 1 ( clk $end
$var wire 16 2 d_in [15:0] $end
$var wire 1 # ld $end
$var reg 16 3 dout [15:0] $end
$upscope $end
$scope module AD $end
$var wire 16 4 in1 [15:0] $end
$var wire 16 5 in2 [15:0] $end
$var reg 16 6 out [15:0] $end
$upscope $end
$scope module B $end
$var wire 1 ( clk $end
$var wire 16 7 data_in [15:0] $end
$var wire 1 & decB $end
$var wire 1 " ld $end
$var reg 16 8 Bout [15:0] $end
$upscope $end
$scope module COMP $end
$var wire 16 9 Bout [15:0] $end
$var wire 1 $ equalZ $end
$upscope $end
$scope module P $end
$var wire 1 ( clk $end
$var wire 1 ' clr $end
$var wire 16 : din [15:0] $end
$var wire 1 ! ld $end
$var reg 16 ; dout [15:0] $end
$upscope $end
$upscope $end
$upscope $end
$enddefinitions $end
#0
$dumpvars
bx ;
bx :
bx 9
bx 8
bx 7
bx 6
bx 5
bx 4
bx 3
bx 2
bx 1
bx 0
bx /
bx .
bx -
bx ,
bx +
x*
bx )
0(
x'
x&
x%
x$
x#
x"
x!
$end
#3000
1*
#5000
b0 +
1(
#6000
0&
0'
0!
0"
0#
#10000
0(
b1111 ,
b1111 2
b1111 7
b1111 )
b1111 -
#15000
b1 +
1(
#16000
1#
#20000
0(
#25000
b1111 0
b1111 3
b1111 4
b10 +
1(
#26000
1'
1"
0#
#30000
0(
b1001 ,
b1001 2
b1001 7
b1001 )
b1001 -
#35000
b1111 .
b1111 6
b1111 :
b11 +
0$
b1001 1
b1001 8
b1001 9
b0 /
b0 5
b0 ;
1(
#36000
1&
0'
1!
0"
#40000
0(
#45000
b11110 .
b11110 6
b11110 :
b1111 /
b1111 5
b1111 ;
b1000 1
b1000 8
b1000 9
1(
#50000
0(
#55000
b101101 .
b101101 6
b101101 :
b111 1
b111 8
b111 9
b11110 /
b11110 5
b11110 ;
1(
#60000
0(
#65000
b111100 .
b111100 6
b111100 :
b101101 /
b101101 5
b101101 ;
b110 1
b110 8
b110 9
1(
#70000
0(
#75000
b1001011 .
b1001011 6
b1001011 :
b101 1
b101 8
b101 9
b111100 /
b111100 5
b111100 ;
1(
#80000
0(
#85000
b1011010 .
b1011010 6
b1011010 :
b1001011 /
b1001011 5
b1001011 ;
b100 1
b100 8
b100 9
1(
#90000
0(
#95000
b1101001 .
b1101001 6
b1101001 :
b11 1
b11 8
b11 9
b1011010 /
b1011010 5
b1011010 ;
1(
#100000
0(
#105000
b1111000 .
b1111000 6
b1111000 :
b1101001 /
b1101001 5
b1101001 ;
b10 1
b10 8
b10 9
1(
#110000
0(
#115000
b10000111 .
b10000111 6
b10000111 :
1$
b1 1
b1 8
b1 9
b1111000 /
b1111000 5
b1111000 ;
1(
#120000
0(
#125000
b10010110 .
b10010110 6
b10010110 :
b10000111 /
b10000111 5
b10000111 ;
0$
b0 1
b0 8
b0 9
b100 +
1(
#126000
0&
0!
1%
